aoe2_telegram_bot/__init__.py
aoe2_telegram_bot/__main__.py
aoe2_telegram_bot/_bot.py
aoe2_telegram_bot/_files_id_db.py
aoe2_telegram_bot/_folders.py
aoe2_telegram_bot/_handlers.py
aoe2_telegram_bot/bootstrap.py
aoe2_telegram_bot/distro/aoe2-telegram-bot.service
aoe2_telegram_bot/images/aoe2-ico.png
aoe2_telegram_bot/images/aoe2-logo.png
aoe2_telegram_bot/images/aok-ico.png
aoe2_telegram_bot/images/conquerors-ico.png
aoe2_telegram_bot-0.3.0.dist-info/entry_points.txt
aoe2_telegram_bot-0.3.0.dist-info/licenses/LICENSE
aoe2_telegram_bot-0.3.0.dist-info/WHEEL
aoe2_telegram_bot-0.3.0.dist-info/METADATA
aoe2_telegram_bot-0.3.0.dist-info/RECORD
