Metadata-Version: 2.4
Name: aoe2_telegram_bot
Version: 0.3.0
Summary: A Telegram Bot that gives a random quote of Age of Empires 2 original edition
Author-email: Perceval ARENOU <perceval.arenou@gmail.com>
Requires-Python: >=3.9
Classifier: Development Status :: 4 - Beta
Classifier: Intended Audience :: End Users/Desktop
Classifier: Intended Audience :: Developers
Classifier: Topic :: Communications :: Chat
Classifier: Topic :: Games/Entertainment
Classifier: License :: OSI Approved :: GNU General Public License v3 (GPLv3)
Classifier: Programming Language :: Python :: 3
Classifier: Programming Language :: Python :: 3.9
Classifier: Programming Language :: Python :: 3.10
Classifier: Programming Language :: Python :: 3.11
Classifier: Programming Language :: Python :: 3.12
Classifier: Operating System :: POSIX :: Linux
Classifier: Operating System :: OS Independent
Classifier: Environment :: No Input/Output (Daemon)
Classifier: Natural Language :: English
Classifier: Natural Language :: French
License-File: LICENSE
Requires-Dist: python-telegram-bot>=v20.0
Requires-Dist: requests>=2.31.0
Requires-Dist: pytest>=7.4.0 ; extra == "test"
Requires-Dist: pytest-asyncio>=0.21.0 ; extra == "test"
Requires-Dist: pytest-cov>=4.1.0 ; extra == "test"
Requires-Dist: pytest-mock>=3.11.0 ; extra == "test"
Project-URL: Homepage, https://github.com/PercevalSA/aoe2-telegram-bot
Project-URL: Issues, https://github.com/PercevalSA/aoe2-telegram-bot/issues
Provides-Extra: test
